oarepo_model_builder_expansions/__init__.py
oarepo_model_builder_expansions/invenio/__init__.py
oarepo_model_builder_expansions/invenio/invenio_expansions_record_service_config.py
oarepo_model_builder_expansions/invenio/templates/invenio_record_service_config.py.jinja2
oarepo_model_builder_expansions/model_preprocessors/__init__.py
oarepo_model_builder_expansions/model_preprocessors/invenio_expansions_base_classes.py
oarepo_model_builder_expansions/validation/__init__.py
oarepo_model_builder_expansions-3.0.2.dist-info/METADATA
oarepo_model_builder_expansions-3.0.2.dist-info/WHEEL
oarepo_model_builder_expansions-3.0.2.dist-info/entry_points.txt
oarepo_model_builder_expansions-3.0.2.dist-info/top_level.txt
oarepo_model_builder_expansions-3.0.2.dist-info/RECORD
