Metadata-Version: 2.1
Name: oarepo-model-builder-expansions
Version: 3.0.2
Requires-Dist: oarepo-model-builder-tests (>=3.1.0)
Provides-Extra: tests
Requires-Dist: pytest-invenio (>=1.4.11) ; extra == 'tests'
